artificial_detection/README.md
artificial_detection/__init__.py
artificial_detection/arguments.py
artificial_detection/data/README.md
artificial_detection/data/__init__.py
artificial_detection/data/const.py
artificial_detection/data/datasets.py
artificial_detection/data/factory.py
artificial_detection/data/generate.py
artificial_detection/data/generate_language_model.py
artificial_detection/models/README.md
artificial_detection/models/__init__.py
artificial_detection/models/const.py
artificial_detection/models/detectors.py
artificial_detection/models/language_model.py
artificial_detection/models/smr/__init__.py
artificial_detection/models/smr/core.py
artificial_detection/models/smr/sais.py
artificial_detection/models/translation.py
artificial_detection/models/validate.py
artificial_detection/pipeline.py
artificial_detection/unsupervised_baseline.py
artificial_detection/utils.py
artificial_detection-0.1.0.dist-info/LICENSE
artificial_detection-0.1.0.dist-info/WHEEL
artificial_detection-0.1.0.dist-info/METADATA
artificial_detection-0.1.0.dist-info/RECORD
