Metadata-Version: 2.1
Name: artificial-detection
Version: 0.1.0
Summary: Python framework for artificial text detection with NLP approaches.
Home-page: https://github.com/MaratSaidov/artificial-text-detection
License: MIT
Author: Marat Saidov
Author-email: msaidov1@yandex.ru
Requires-Python: >=3.7.1,<3.10
Classifier: License :: OSI Approved :: MIT License
Classifier: Programming Language :: Python :: 3
Classifier: Programming Language :: Python :: 3.8
Classifier: Programming Language :: Python :: 3.9
Requires-Dist: EasyNMT (==2.0.1)
Requires-Dist: autoflake (==1.4)
Requires-Dist: datasets (==1.15.1)
Requires-Dist: dvc[gdrive] (==2.9.3)
Requires-Dist: filelock (==3.4.2)
Requires-Dist: huggingface (==0.0.1)
Requires-Dist: numpy (==1.21.4)
Requires-Dist: packaging (==21.3)
Requires-Dist: pandas (==1.3.4)
Requires-Dist: requests (==2.27.1)
Requires-Dist: scikit-learn (==1.0.1)
Requires-Dist: sklearn (==0.0)
Requires-Dist: torch (==1.10.1)
Requires-Dist: transformers (==4.12.3)
Requires-Dist: wandb (==0.12.6)
